<?xml version='1.0' encoding='UTF-8'?>
<!DOCTYPE hibernate-configuration PUBLIC
          "-//Hibernate/Hibernate Configuration DTD 3.0//EN"
          "http://hibernate.sourceforge.net/hibernate-configuration-3.0.dtd">

<!-- Generated by MyEclipse Hibernate Tools.                   -->
<hibernate-configuration>

	<session-factory>
		<property name="connection.username">{user}</property>
		<property name="connection.url">
			{url}
		</property>
		<property name="dialect">
			{dialect}
		</property>
		<property name="connection.password">{pass}</property>
		<property name="connection.driver_class">
			{driver}
		</property>

		<mapping resource="sernet/gs/reveng/NmbNotiz.hbm.xml" />
		<mapping resource="sernet/gs/reveng/NZielobjekt.hbm.xml" />
		<mapping resource="sernet/gs/reveng/MbZielobjTyp.hbm.xml" />
		<mapping resource="sernet/gs/reveng/MsCmState.hbm.xml" />
		<mapping resource="sernet/gs/reveng/MMetatyp.hbm.xml" />
		<mapping resource="sernet/gs/reveng/MbDringlichkeit.hbm.xml" />
		<mapping resource="sernet/gs/reveng/MUmsetzStat.hbm.xml" />
		<mapping resource="sernet/gs/reveng/MYesno.hbm.xml" />
		<mapping resource="sernet/gs/reveng/SysImport.hbm.xml" />
		<mapping resource="sernet/gs/reveng/MbZielobjSubtyp.hbm.xml" />
		<mapping resource="sernet/gs/reveng/MGsiegel.hbm.xml" />
		<mapping resource="sernet/gs/reveng/MbStatus.hbm.xml" />
		<mapping resource="sernet/gs/reveng/MMetastatus.hbm.xml" />
		<mapping resource="sernet/gs/reveng/MbZielobjTypTxt.hbm.xml" />
		<mapping resource="sernet/gs/reveng/ModZobjBst.hbm.xml" />
		<mapping resource="sernet/gs/reveng/MBstnStatus.hbm.xml" />
		<mapping resource="sernet/gs/reveng/MbBaust.hbm.xml" />
		<mapping resource="sernet/gs/reveng/MbSchicht.hbm.xml" />
		<mapping resource="sernet/gs/reveng/ModZobjBstMass.hbm.xml" />
		<mapping resource="sernet/gs/reveng/MUmsetzStatTxt.hbm.xml" />
		<mapping resource="sernet/gs/reveng/MbMassn.hbm.xml" />
		<mapping resource="sernet/gs/reveng/MbZielobjSubtypTxt.hbm.xml" />
		<mapping resource="sernet/gs/reveng/MbZeiteinheitenTxt.hbm.xml" />
		<mapping
			resource="sernet/gs/reveng/ModZobjBstMassMitarb.hbm.xml" />
		<mapping resource="sernet/gs/reveng/MbRolleTxt.hbm.xml" />
		<mapping resource="sernet/gs/reveng/NZielobjektRollen.hbm.xml" />
		<mapping resource="sernet/gs/reveng/NZielobjZielobj.hbm.xml" />
		<mapping resource="sernet/gs/reveng/NZobSb.hbm.xml" />
		<mapping
			resource="sernet/gs/reveng/MSchutzbedarfkategTxt.hbm.xml" />
		<mapping resource="sernet/gs/reveng/ModZobjBstMitarb.hbm.xml" />
		<mapping resource="sernet/gs/reveng/MbDringlichkeitTxt.hbm.xml" />
			
	</session-factory>

</hibernate-configuration>
